djvite/__init__.py
djvite/apps.py
djvite/management/__init__.py
djvite/management/commands/__init__.py
djvite/management/commands/get_nginx_config.py
djvite/py.typed
djvite/templatetags/__init__.py
djvite/templatetags/djvite.py
djvite-1.5.0.dist-info/licenses/LICENSE
djvite-1.5.0.dist-info/WHEEL
djvite-1.5.0.dist-info/METADATA
djvite-1.5.0.dist-info/RECORD
