Metadata-Version: 2.4
Name: djvite
Version: 1.5.0
Summary: Integrates Vite resources into a Django web site.
Keywords: django,vite,javascript
Author: Cyrille Pontvieux
Author-email: Cyrille Pontvieux <cyrille@enialis.net>
License-Expression: MIT
License-File: LICENSE
Classifier: Development Status :: 5 - Production/Stable
Classifier: Intended Audience :: Developers
Classifier: Natural Language :: English
Classifier: Operating System :: OS Independent
Classifier: Environment :: Web Environment
Classifier: Programming Language :: Python :: 3.12
Classifier: Programming Language :: Python :: 3.13
Classifier: Programming Language :: Python :: 3.14
Classifier: Programming Language :: JavaScript
Classifier: Framework :: Django
Classifier: Framework :: Django :: 4.2
Classifier: Framework :: Django :: 5.0
Classifier: Framework :: Django :: 5.1
Classifier: Framework :: Django :: 5.2
Classifier: Framework :: Django :: 6.0
Classifier: Topic :: Software Development :: Build Tools
Classifier: Typing :: Typed
Requires-Dist: django>=4.2
Requires-Python: >=3.12
Project-URL: Bug Tracker, https://gitlab.com/snake_coders/djvite/-/issues
Project-URL: Changelog, https://gitlab.com/snake_coders/djvite/-/blob/master/CHANGELOG.md
Project-URL: Contributing, https://gitlab.com/snake_coders/djvite/-/blob/master/CONTRIBUTING.md
Project-URL: Documentation, https://gitlab.com/snake_coders/djvite/-/blob/master/README.md
Project-URL: Merge Requests, https://gitlab.com/snake_coders/djvite/-/merge_requests
Project-URL: Repository, https://gitlab.com/snake_coders/djvite
